setup.py
django_hybridstorage.egg-info/PKG-INFO
django_hybridstorage.egg-info/SOURCES.txt
django_hybridstorage.egg-info/dependency_links.txt
django_hybridstorage.egg-info/top_level.txt
hybridstorage/__init__.py
hybridstorage/models.py
hybridstorage/storages.py
hybridstorage/tests.py