Metadata-Version: 1.0
Name: django-hybridstorage
Version: 1.1.0
Summary: Use multiple file storages to serve and store files
Home-page: http://github.com/eofs/django-hybridstorage/
Author: Tomi Pajunen
Author-email: tomi@madlab.fi
License: BSD
Platform: UNKNOWN
